pyvector/__init__.py
pyvector-0.1.3.dist-info/LICENSE
pyvector-0.1.3.dist-info/METADATA
pyvector-0.1.3.dist-info/WHEEL
pyvector-0.1.3.dist-info/top_level.txt
pyvector-0.1.3.dist-info/RECORD
