Metadata-Version: 2.1
Name: pyvector
Version: 0.1.3
Summary: Simple classes for SVG generation
Home-page: http://github.com/thoelken/pyvector
Author: Clemens Thölken
Author-email: code@tholken.org
License: MIT
Keywords: SVG vector graphics
Platform: UNKNOWN
License-File: LICENSE
